INSTALL
MANIFEST.in
README.rst
setup.cfg
setup.py
./__init__.py
./party.py
./party.xml
./tryton.cfg
./tests/__init__.py
./tests/test_party.py
./tests/test_views_depends.py
./view/badge_form.xml
./view/badge_tree.xml
./view/party_form.xml
trytonacs_party_access_control.egg-info/PKG-INFO
trytonacs_party_access_control.egg-info/SOURCES.txt
trytonacs_party_access_control.egg-info/dependency_links.txt
trytonacs_party_access_control.egg-info/entry_points.txt
trytonacs_party_access_control.egg-info/not-zip-safe
trytonacs_party_access_control.egg-info/requires.txt
trytonacs_party_access_control.egg-info/top_level.txt